Workbook

Sheet Dashboard
B2: CHECK LIST DE SUPERVISIÓN — SOFT RESTAURANT 12
B5: Fogueira • Supervisora: Mónica Solís • Meta: pasar del 62 % al 100 % de aprovechamiento
B7: AVANCE GLOBAL HACIA EL 100 %
B8: =ROUND(0.62 + (1-0.62)*((Diario!H1+Semanal!H1+Mensual!H1)/3),3) -> 0.62
B12: ="Línea base auditoría: 62 % • Brecha por cerrar: "&TEXT(1-B8,"0.0%")&" • Fecha de revisión: "&TEXT(TODAY(),"dd/mm/yyyy") -> Línea base auditoría: 62 % • Brecha por cerrar: 38.0% • Fecha de revisión: 07/05/2026
B14: AVANCE POR FRECUENCIA DE REVISIÓN
B15: Diario | D15: Semanal | F15: Mensual
B18: =Diario!H1 -> 0 | D18: =Semanal!H1 -> 0 | F18: =Mensual!H1 -> 0
B19: =COUNTIF(Diario!F5:L18,1)&" cumplidas / "&(COUNTA(Diario!E5:E18)*7)&" posibles" -> 0 cumplidas / 98 posibles | D19: =COUNTIF(Semanal!F5:I15,1)&" cumplidas / "&(COUNTA(Semanal!E5:E15)*4)&" posibles" -> 0 cumplidas / 44 posibles | F19: =COUNTIF(Mensual!F5:Q15,1)&" cumplidas / "&(COUNTA(Mensual!E5:E15)*12)&" posibles" -> 0 cumplidas / 132 posibles
B21: AVANCE POR ÁREA / RESPONSABLE
B22: Área | C22: Diario | D22: Semanal | E22: Mensual | F22: Promedio área | H22: Avanzado | I22: =B8 -> 0.62
B23: POS / Cajero | C23: =IFERROR(SUMIFS(Diario!O5:O100,Diario!C5:C100,"*"&B23&"*")/COUNTIFS(Diario!C5:C100,"*"&B23&"*"),0) -> 0 | D23: =IFERROR(SUMIFS(Semanal!L5:L100,Semanal!C5:C100,"*"&B23&"*")/COUNTIFS(Semanal!C5:C100,"*"&B23&"*"),0) -> 0 | E23: =IFERROR(SUMIFS(Mensual!T5:T100,Mensual!C5:C100,"*"&B23&"*")/COUNTIFS(Mensual!C5:C100,"*"&B23&"*"),0) -> 0 | F23: =IFERROR(AVERAGE(C23:E23),0) -> 0 | H23: Brecha | I23: =1-B8 -> 0.38
B24: Almacén | C24: =IFERROR(SUMIFS(Diario!O5:O100,Diario!C5:C100,"*"&B24&"*")/COUNTIFS(Diario!C5:C100,"*"&B24&"*"),0) -> 0 | D24: =IFERROR(SUMIFS(Semanal!L5:L100,Semanal!C5:C100,"*"&B24&"*")/COUNTIFS(Semanal!C5:C100,"*"&B24&"*"),0) -> 0 | E24: =IFERROR(SUMIFS(Mensual!T5:T100,Mensual!C5:C100,"*"&B24&"*")/COUNTIFS(Mensual!C5:C100,"*"&B24&"*"),0) -> 0 | F24: =IFERROR(AVERAGE(C24:E24),0) -> 0
B25: Compras | C25: =IFERROR(SUMIFS(Diario!O5:O100,Diario!C5:C100,"*"&B25&"*")/COUNTIFS(Diario!C5:C100,"*"&B25&"*"),0) -> 0 | D25: =IFERROR(SUMIFS(Semanal!L5:L100,Semanal!C5:C100,"*"&B25&"*")/COUNTIFS(Semanal!C5:C100,"*"&B25&"*"),0) -> 0 | E25: =IFERROR(SUMIFS(Mensual!T5:T100,Mensual!C5:C100,"*"&B25&"*")/COUNTIFS(Mensual!C5:C100,"*"&B25&"*"),0) -> 0 | F25: =IFERROR(AVERAGE(C25:E25),0) -> 0 | H25: Frecuencia | I25: Avance
B26: Cocina | C26: =IFERROR(SUMIFS(Diario!O5:O100,Diario!C5:C100,"*"&B26&"*")/COUNTIFS(Diario!C5:C100,"*"&B26&"*"),0) -> 0 | D26: =IFERROR(SUMIFS(Semanal!L5:L100,Semanal!C5:C100,"*"&B26&"*")/COUNTIFS(Semanal!C5:C100,"*"&B26&"*"),0) -> 0 | E26: =IFERROR(SUMIFS(Mensual!T5:T100,Mensual!C5:C100,"*"&B26&"*")/COUNTIFS(Mensual!C5:C100,"*"&B26&"*"),0) -> 0 | F26: =IFERROR(AVERAGE(C26:E26),0) -> 0 | H26: Diario | I26: =Diario!H1 -> 0
B27: Gerencia | C27: =IFERROR(SUMIFS(Diario!O5:O100,Diario!C5:C100,"*"&B27&"*")/COUNTIFS(Diario!C5:C100,"*"&B27&"*"),0) -> 0 | D27: =IFERROR(SUMIFS(Semanal!L5:L100,Semanal!C5:C100,"*"&B27&"*")/COUNTIFS(Semanal!C5:C100,"*"&B27&"*"),0) -> 0 | E27: =IFERROR(SUMIFS(Mensual!T5:T100,Mensual!C5:C100,"*"&B27&"*")/COUNTIFS(Mensual!C5:C100,"*"&B27&"*"),0) -> 0 | F27: =IFERROR(AVERAGE(C27:E27),0) -> 0 | H27: Semanal | I27: =Semanal!H1 -> 0
H28: Mensual | I28: =Mensual!H1 -> 0
B49: C.P. Germán Solís Zamora — Auditor Interno • Grupo Toda • Folio: AUD-2025-FOG-001

Sheet Diario
H1: =IFERROR(AVERAGE(M5:M18),0) -> 0
B2: CHECK LIST DIARIO — SR12 FOGUEIRA
B3: Marca 1 = cumplido • 0 = no cumplido • vacío = no revisado. El Dashboard se actualiza solo.
B4: # | C4: Puesto | D4: Responsable | E4: Verificación | F4: Lun | G4: Mar | H4: Mié | I4: Jue | J4: Vie | K4: Sáb | L4: Dom | M4: % cumplimiento | N4: Notas / hallazgos | O4: _pct_fila
B5: 1 | C5: POS / Cajero | D5: Cajero en turno | E5: ¿Se imprimió y archivó el Corte Z al cierre del turno? | M5: =IFERROR(COUNTIF(F5:L5,1)/COUNTA(F5:L5),0) -> 0 | O5: =M5 -> 0
B6: 2 | C6: POS / Cajero | D6: Cajero en turno | E6: ¿Cuadró el efectivo del POS contra la caja física? (diferencia ≤ $50) | M6: =IFERROR(COUNTIF(F6:L6,1)/COUNTA(F6:L6),0) -> 0 | O6: =M6 -> 0
B7: 3 | C7: POS / Cajero | D7: Cajero en turno | E7: ¿Todas las cuentas/comandas del día quedaron cerradas? (ninguna abierta) | M7: =IFERROR(COUNTIF(F7:L7,1)/COUNTA(F7:L7),0) -> 0 | O7: =M7 -> 0
B8: 4 | C8: POS / Cajero | D8: Cajero en turno | E8: ¿Cancelaciones del día están justificadas y autorizadas por gerente? | M8: =IFERROR(COUNTIF(F8:L8,1)/COUNTA(F8:L8),0) -> 0 | O8: =M8 -> 0
B9: 5 | C9: Almacén | D9: Almacenista | E9: ¿Se capturaron en SR12 todas las entradas de mercancía recibidas hoy? | M9: =IFERROR(COUNTIF(F9:L9,1)/COUNTA(F9:L9),0) -> 0 | O9: =M9 -> 0
B10: 6 | C10: Almacén | D10: Almacenista | E10: ¿Se registraron las salidas/traspasos del día (cocina, bar, sub-almacenes)? | M10: =IFERROR(COUNTIF(F10:L10,1)/COUNTA(F10:L10),0) -> 0 | O10: =M10 -> 0
B11: 7 | C11: Almacén | D11: Almacenista | E11: ¿Se registraron las mermas y desperdicios del día (si los hubo)? | M11: =IFERROR(COUNTIF(F11:L11,1)/COUNTA(F11:L11),0) -> 0 | O11: =M11 -> 0
B12: 8 | C12: Almacén | D12: Almacenista | E12: ¿Refrigeradores con temperatura registrada en bitácora? (≤ 4 °C / ≤ -18 °C) | M12: =IFERROR(COUNTIF(F12:L12,1)/COUNTA(F12:L12),0) -> 0 | O12: =M12 -> 0
B13: 9 | C13: Compras | D13: Comprador | E13: ¿Cada factura recibida hoy quedó capturada en SR12 con su orden de compra? | M13: =IFERROR(COUNTIF(F13:L13,1)/COUNTA(F13:L13),0) -> 0 | O13: =M13 -> 0
B14: 10 | C14: Compras | D14: Comprador | E14: ¿Las compras del día tienen precio actualizado en el catálogo? | M14: =IFERROR(COUNTIF(F14:L14,1)/COUNTA(F14:L14),0) -> 0 | O14: =M14 -> 0
B15: 11 | C15: Cocina | D15: Chef en turno | E15: ¿Se reportaron mermas y desperdicios del turno con foto/firma? | M15: =IFERROR(COUNTIF(F15:L15,1)/COUNTA(F15:L15),0) -> 0 | O15: =M15 -> 0
B16: 12 | C16: Cocina | D16: Chef en turno | E16: ¿Hubo platos vendidos sin receta cargada en SR12? (debe ser CERO) | M16: =IFERROR(COUNTIF(F16:L16,1)/COUNTA(F16:L16),0) -> 0 | O16: =M16 -> 0
... B18: 14 | C18: Gerencia | D18: Mónica Solís | E18: ¿Se revisó el reporte de descuentos/cortesías del día? | M18: =IFERROR(COUNTIF(F18:L18,1)/COUNTA(F18:L18),0) -> 0 | O18: =M18 -> 0

Sheet Semanal
H1: =IFERROR(AVERAGE(J5:J15),0) -> 0
B2: CHECK LIST SEMANAL — SR12 FOGUEIRA
B3: Marca 1 = cumplido • 0 = no cumplido • vacío = no revisado. El Dashboard se actualiza solo.
B4: # | C4: Puesto | D4: Responsable | E4: Verificación | F4: Sem 1 | G4: Sem 2 | H4: Sem 3 | I4: Sem 4 | J4: % cumplimiento | K4: Notas / hallazgos | L4: _pct_fila
B5: 1 | C5: Almacén | D5: Almacenista | E5: Conteo cíclico semanal de al menos 1 sección (rotando). | J5: =IFERROR(COUNTIF(F5:I5,1)/COUNTA(F5:I5),0) -> 0 | L5: =J5 -> 0
B6: 2 | C6: Almacén | D6: Almacenista | E6: Top 10 productos críticos: saldo SR12 vs físico. Diferencia ≤ 2 %. | J6: =IFERROR(COUNTIF(F6:I6,1)/COUNTA(F6:I6),0) -> 0 | L6: =J6 -> 0
B7: 3 | C7: Almacén | D7: Almacenista | E7: Inventario teórico de bar al cierre semanal. | J7: =IFERROR(COUNTIF(F7:I7,1)/COUNTA(F7:I7),0) -> 0 | L7: =J7 -> 0
B8: 4 | C8: Compras | D8: Comprador | E8: Conciliar facturas del proveedor contra OC y entradas (3-way match). | J8: =IFERROR(COUNTIF(F8:I8,1)/COUNTA(F8:I8),0) -> 0 | L8: =J8 -> 0
B9: 5 | C9: Compras | D9: Comprador | E9: Actualizar precios de insumos críticos (top 20 por valor). | J9: =IFERROR(COUNTIF(F9:I9,1)/COUNTA(F9:I9),0) -> 0 | L9: =J9 -> 0
B10: 6 | C10: POS / Cocina | D10: Chef + Cajero | E10: Revisar que los 20 platos más vendidos tengan receta vigente cargada. | J10: =IFERROR(COUNTIF(F10:I10,1)/COUNTA(F10:I10),0) -> 0 | L10: =J10 -> 0
B11: 7 | C11: POS / Cocina | D11: Chef | E11: Cargar en SR12 las recetas de cualquier plato nuevo introducido. | J11: =IFERROR(COUNTIF(F11:I11,1)/COUNTA(F11:I11),0) -> 0 | L11: =J11 -> 0
B12: 8 | C12: POS / Cajero | D12: Cajero | E12: Revisar descuentos/cancelaciones de la semana y validar autorización. | J12: =IFERROR(COUNTIF(F12:I12,1)/COUNTA(F12:I12),0) -> 0 | L12: =J12 -> 0
B13: 9 | C13: Cocina | D13: Chef | E13: Análisis semanal de mermas por categoría (proteína, lácteos, vegetales). | J13: =IFERROR(COUNTIF(F13:I13,1)/COUNTA(F13:I13),0) -> 0 | L13: =J13 -> 0
B14: 10 | C14: Gerencia | D14: Mónica Solís | E14: Reunión semanal de KPIs con responsables de área. | J14: =IFERROR(COUNTIF(F14:I14,1)/COUNTA(F14:I14),0) -> 0 | L14: =J14 -> 0
B15: 11 | C15: Gerencia | D15: Mónica Solís | E15: Revisar margen bruto semanal y comparar contra meta. | J15: =IFERROR(COUNTIF(F15:I15,1)/COUNTA(F15:I15),0) -> 0 | L15: =J15 -> 0

Sheet Mensual
H1: =IFERROR(AVERAGE(R5:R15),0) -> 0
B2: CHECK LIST MENSUAL — SR12 FOGUEIRA
B3: Marca 1 = cumplido • 0 = no cumplido • vacío = no revisado. El Dashboard se actualiza solo.
B4: # | C4: Puesto | D4: Responsable | E4: Verificación | F4: Ene | G4: Feb | H4: Mar | I4: Abr | J4: May | K4: Jun | L4: Jul | M4: Ago | N4: Sep | O4: Oct | P4: Nov | Q4: Dic | R4: % cumplimiento | S4: Notas / hallazgos | T4: _pct_fila
B5: 1 | C5: Almacén | D5: Almacenista | E5: Inventario físico mensual completo (almacén general + sub-almacenes + bar). | R5: =IFERROR(COUNTIF(F5:Q5,1)/COUNTA(F5:Q5),0) -> 0 | T5: =R5 -> 0
B6: 2 | C6: Almacén | D6: Almacenista + Mónica | E6: Diferencias > 2 % con justificación documentada y firma. | R6: =IFERROR(COUNTIF(F6:Q6,1)/COUNTA(F6:Q6),0) -> 0 | T6: =R6 -> 0
B7: 3 | C7: Compras | D7: Comprador + Contabilidad | E7: Conciliación de cuentas por pagar contra estados del proveedor. | R7: =IFERROR(COUNTIF(F7:Q7,1)/COUNTA(F7:Q7),0) -> 0 | T7: =R7 -> 0
B8: 4 | C8: Compras | D8: Comprador | E8: Catálogo de proveedores revisado y actualizado. | R8: =IFERROR(COUNTIF(F8:Q8,1)/COUNTA(F8:Q8),0) -> 0 | T8: =R8 -> 0
B9: 5 | C9: POS | D9: Cajero + Mónica | E9: Conciliación POS vs caja chica del mes. | R9: =IFERROR(COUNTIF(F9:Q9,1)/COUNTA(F9:Q9),0) -> 0 | T9: =R9 -> 0
B10: 6 | C10: POS | D10: Cajero | E10: Reporte de productos sin movimiento del mes. | R10: =IFERROR(COUNTIF(F10:Q10,1)/COUNTA(F10:Q10),0) -> 0 | T10: =R10 -> 0
B11: 7 | C11: Cocina | D11: Chef | E11: Análisis mensual de mermas por categoría con plan de acción. | R11: =IFERROR(COUNTIF(F11:Q11,1)/COUNTA(F11:Q11),0) -> 0 | T11: =R11 -> 0
B12: 8 | C12: Cocina | D12: Chef | E12: Re-costeo mensual de recetas con precios vigentes de insumos. | R12: =IFERROR(COUNTIF(F12:Q12,1)/COUNTA(F12:Q12),0) -> 0 | T12: =R12 -> 0
B13: 9 | C13: Gerencia | D13: Mónica Solís | E13: Cierre mensual ejecutado en SR12 (cierre contable / inventarios). | R13: =IFERROR(COUNTIF(F13:Q13,1)/COUNTA(F13:Q13),0) -> 0 | T13: =R13 -> 0
B14: 10 | C14: Gerencia | D14: Mónica Solís | E14: Reporte gerencial mensual generado y firmado por Contralor. | R14: =IFERROR(COUNTIF(F14:Q14,1)/COUNTA(F14:Q14),0) -> 0 | T14: =R14 -> 0
B15: 11 | C15: Gerencia | D15: Mónica Solís | E15: Junta mensual de revisión de avance de Plan de Remediación. | R15: =IFERROR(COUNTIF(F15:Q15,1)/COUNTA(F15:Q15),0) -> 0 | T15: =R15 -> 0

Sheet Bitácora
B2: BITÁCORA DE HALLAZGOS — SUPERVISIÓN SR12
B3: Mónica anota aquí cualquier desviación detectada durante la supervisión. Cada hallazgo debe tener responsable y fecha compromiso.
B4: # | C4: Fecha | D4: Puesto | E4: Responsable | F4: Hallazgo / desviación | G4: Acción acordada | H4: Compromiso (fecha) | I4: Estatus
B5: 1
B6: 2
B7: 3
B8: 4
B9: 5
B10: 6
B11: 7
B12: 8
B13: 9
B14: 10
B15: 11
B16: 12
... B34: 30

Sheet Cómo usarlo
B2: CÓMO USAR ESTE CHECK LIST
B4: ¿Para qué sirve?
B5: Este archivo es la herramienta diaria de Mónica Solís para supervisar que el Sistema Soft Restaurant 12 se use correctamente en Fogueira. Hoy estamos en 62 % de aprovechamiento; cada casilla marcada acerca a la operación al 100 %.
B7: ¿Cómo se llena?
B8: Cada vez que Mónica revise un punto, escribe en la casilla: 1 → se cumplió 0 → no se cumplió (vacío) → no se revisó hoy/esta semana/este mes Las casillas se pintan automáticamente: verde = cumplido, rojo = no cumplido.
B10: ¿Qué pasa con las gráficas?
B11: Las gráficas del Dashboard se actualizan SOLAS cada vez que se marca una casilla. No hay que hacer nada manual. El % global combina los tres niveles (diario, semanal, mensual) ponderados sobre la línea base del 62 %.
B13: ¿Qué hacer si encuentras un fallo?
B14: Marcar la casilla con 0, escribir una nota corta en la columna 'Notas / hallazgos' y pasarlo a la hoja 'Bitácora' con responsable y fecha compromiso. El estatus se controla con la lista (Abierto / En proceso / Cerrado).
B16: ¿Cada cuánto se revisa?
B17: Diario: al cierre de cada turno (POS, almacén, cocina, gerencia). Semanal: cada lunes por la mañana, antes de la junta de KPIs. Mensual: durante el cierre mensual junto con Yonder (Contralor).
B19: ¿Quién valida?
... B23: Para saber si alguien está cumpliendo, ve a la hoja Dashboard → tabla 'Avance por área'. Verde ≥ 80 % = bien, ámbar 50-79 % = atención, rojo < 50 % = intervención inmediata.
